[
  {
    "name": "第六屆幹事",
    "image": "images/members/6.jpg",
    "members": [
      {
        "chinese": "古家麗",
        "english": null,
        "year": 2014,
        "position": "會長"
      },
      {
        "chinese": "蔡文建",
        "english": null,
        "year": 2014,
        "position": "內務副會長"
      },
      {
        "chinese": "李振煌",
        "english": null,
        "year": 2014,
        "position": "外務副會長"
      },
      {
        "chinese": "羅朗鐳",
        "english": null,
        "year": 2014,
        "position": "財政"
      },
      {
        "chinese": "關秀華",
        "english": null,
        "year": 2014,
        "position": "常務"
      },
      {
        "chinese": "張智匤",
        "english": null,
        "year": 2014,
        "position": "內務秘書"
      },
      {
        "chinese": "陳瑩瑩",
        "english": null,
        "year": 2014,
        "position": "出版"
      },
      {
        "chinese": "鄭曉彤",
        "english": null,
        "year": 2014,
        "position": "出版"
      },
      {
        "chinese": "曹啓謙",
        "english": null,
        "year": 2014,
        "position": "康樂及聯絡"
      },
      {
        "chinese": "羅煒國",
        "english": null,
        "year": 2014,
        "position": "康樂及聯絡"
      },
      {
        "chinese": "陳凱盈",
        "english": null,
        "year": 2014,
        "position": "福利"
      }
    ]
  },
  {
    "name": "第五屆幹事",
    "members": [
      {
        "chinese": "鄭傳光",
        "english": null,
        "year": 2013,
        "position": "會長"
      },
      {
        "chinese": "曾慶山",
        "english": null,
        "year": 2013,
        "position": "內務副會長"
      },
      {
        "chinese": "莫志雄",
        "english": null,
        "year": 2013,
        "position": "財政"
      },
      {
        "chinese": "鍾穎琪",
        "english": null,
        "year": 2013,
        "position": "秘書"
      },
      {
        "chinese": "黃思欣",
        "english": null,
        "year": 2013,
        "position": "秘書"
      },
      {
        "chinese": "馮國偉",
        "english": null,
        "year": 2013,
        "position": "出版"
      },
      {
        "chinese": "袁茂生",
        "english": null,
        "year": 2013,
        "position": "康樂"
      },
      {
        "chinese": "林卓賢",
        "english": null,
        "year": 2013,
        "position": "聯絡"
      },
      {
        "chinese": "張耀文",
        "english": null,
        "year": 2013,
        "position": "福利"
      }
    ]
  },
  {
    "name": "第四屆幹事",
    "members": [
      {
        "chinese": "楊毓瑋",
        "english": null,
        "year": null,
        "position": "會長"
      },
      {
        "chinese": "葉佩穎",
        "english": null,
        "year": null,
        "position": "內務副會長"
      },
      {
        "chinese": "甄力恒",
        "english": null,
        "year": null,
        "position": "外務副會長"
      },
      {
        "chinese": "伍耀輝",
        "english": null,
        "year": null,
        "position": "財政"
      },
      {
        "chinese": "張翠兒",
        "english": null,
        "year": null,
        "position": "常務秘書"
      },
      {
        "chinese": "李曉珊",
        "english": null,
        "year": null,
        "position": "內務秘書"
      },
      {
        "chinese": "林卓康",
        "english": null,
        "year": null,
        "position": "出版"
      },
      {
        "chinese": "陳富洋",
        "english": null,
        "year": null,
        "position": "康樂及聯絡"
      },
      {
        "chinese": "鍾安娜",
        "english": null,
        "year": null,
        "position": "康樂及聯絡"
      },
      {
        "chinese": "林香琪",
        "english": null,
        "year": null,
        "position": "福利"
      }
    ]
  },
  {
    "name": "第三屆幹事",
    "members": [
      {
        "chinese": "黃梓鍵",
        "english": null,
        "year": null,
        "position": "會長"
      },
      {
        "chinese": "吳芷樺",
        "english": null,
        "year": null,
        "position": "內務副會長"
      },
      {
        "chinese": "李嘉琪",
        "english": null,
        "year": null,
        "position": "外務副會長"
      },
      {
        "chinese": "朱潤華",
        "english": null,
        "year": null,
        "position": "財政"
      },
      {
        "chinese": "鄧敏聰",
        "english": null,
        "year": null,
        "position": "內務秘書"
      },
      {
        "chinese": "吳佳琪",
        "english": null,
        "year": null,
        "position": "常務秘書"
      },
      {
        "chinese": "楊婷婷",
        "english": null,
        "year": null,
        "position": "福利"
      },
      {
        "chinese": "方思灝",
        "english": null,
        "year": null,
        "position": "康樂及聯絡"
      },
      {
        "chinese": "黃健駿",
        "english": null,
        "year": null,
        "position": "出版"
      },
      {
        "chinese": "陳坤毅",
        "english": null,
        "year": null,
        "position": "出版"
      }
    ]
  },
  {
    "name": "第二屆幹事",
    "members": [
      {
        "chinese": "陸倩芝",
        "english": null,
        "year": 2004,
        "position": "會長"
      },
      {
        "chinese": "周瑞年",
        "english": null,
        "year": 2003,
        "position": "內務副主席"
      },
      {
        "chinese": "彭桂玲",
        "english": null,
        "year": 2003,
        "position": "外務副主席"
      },
      {
        "chinese": "陳賢珠",
        "english": null,
        "year": 2003,
        "position": "財政"
      },
      {
        "chinese": "張小花",
        "english": null,
        "year": 2003,
        "position": "聯絡"
      },
      {
        "chinese": "鄧慧貞",
        "english": null,
        "year": 2003,
        "position": "福利"
      },
      {
        "chinese": "謝燕揚",
        "english": null,
        "year": 2004,
        "position": "康樂"
      },
      {
        "chinese": "郭佩玲",
        "english": null,
        "year": 2003,
        "position": "常務秘書"
      },
      {
        "chinese": "嚴慧敏",
        "english": null,
        "year": 2004,
        "position": "常務秘書"
      },
      {
        "chinese": "馬凱婷",
        "english": null,
        "year": 2003,
        "position": "內務秘書"
      },
      {
        "chinese": "賴冠銓",
        "english": null,
        "year": 2004,
        "position": "出版及宣傳"
      }
    ]
  },
  {
    "name": "第一屆幹事",
    "image": "images/members/1.jpg",
    "members": [
      {
        "chinese": "吳婉琪",
        "english": "Krista",
        "year": 1999,
        "position": "會長"
      },
      {
        "chinese": "禤富強",
        "english": "Edward",
        "year": 1999,
        "position": "內務副會長"
      },
      {
        "chinese": "徐定安",
        "english": "Cliff",
        "year": 1999,
        "position": "外務副會長"
      },
      {
        "chinese": "樊泳嫻",
        "english": "Tracy",
        "year": 1999,
        "position": "財政"
      },
      {
        "chinese": "林春美",
        "english": "May",
        "year": 1999,
        "position": "內務秘書"
      },
      {
        "chinese": "梁向暉",
        "english": "Elvis",
        "year": 1999,
        "position": "常務秘書"
      },
      {
        "chinese": "林婉珊",
        "english": "Celia",
        "year": 1999,
        "position": "福利"
      },
      {
        "chinese": "張志藝",
        "english": "Kevin",
        "year": 1999,
        "position": "康樂"
      },
      {
        "chinese": "劉子榮",
        "english": "Terence",
        "year": 1999,
        "position": "聯絡"
      },
      {
        "chinese": "李嘉敏",
        "english": "Carman",
        "year": 1999,
        "position": "出版"
      },
      {
        "chinese": "段夏鷹",
        "english": null,
        "year": 1999,
        "position": "出版"
      }
    ]
  }
]